Workbook

Sheet Overview
A2: Worksheet | B2: Content
A3: Indicator list-QQC structural | B3: Definition and descripton of indicators
A4: 1-QQM_SUMMARY_SHEET | B4: Summary overview of the QQM indicators, per domain and province
A5: 2-QQM_BY ROUND | B5: Provincial QQM structural, outcome and content quality scores, per round and province
A6: Annex 1a - QQC_Structural_PROV | B6: Detailed overview of the scores for QQC structural quality, per province
A7: Annex1b-QQC_Structural_FAC | B7: Detailed overview of the scores for QQC structural quality, per health facility
A8: Annex1c-QQC_Tracerdrugs_PROV | B8: Detailed overview of availability of tracer drugs, per province
A9: Annex2a-QQM_EXIT&VIGNETTES_PROV | B9: Detailed overview of the scores for QQM outcome quality (exit interviews) and content of care(vignettes) indicators, per province
A10: Annex 2b-QQC_EXIT&VIGNETTES_FAC | B10: Detailed overview of the scores for QQM outcome quality (exit interviews) and content of care(vignettes) indicators, per health facility
A11: Annex 3a-HEALTH WORKERS - PROV | B11: Detailed overview of the scores for non-QQM indicators on Staffing (Salary payment, Health staff availability, GBV training, HW satisfaction), per province
A12: Annex 3b-HEALTH WORKERS - FAC | B12: Detailed overview of the scores for non-QQM indicators on Staffing (Salary payment, Health staff availability, GBV training, HW satisfaction), per health facility
A13: Annex 4a-MSS - PROV'!A1 | B13: Detailed overview of the scores for Minimum Standard of Services for health facilities not covered by QQM ( i.e SHC, RH/PH), per province
A14: Annex 4b-MSS - FAC'!A1 | B14: Detailed overview of the scores for Minimum Standard of Services for health facilities not covered by QQM ( i.e SHC, RH/PH), per health facility

Sheet Indicator list
A1: Overview of indicators by assessment
A2: # indicator | B2: Indicator Name | C2: Sub-indicator / Description | D2: Max Points (YES) | E2: Applicable at HFs
A3: QQM Structural Quality - Domain 1: General Management
A4: SQ 1.1 | B4: Presence of map of health facility catchment area | C4: A visually represented health map is displayed on the notice board of a health facility. The map includes population data, details of other health facilities in the area, villages, main roads, natural barriers, special points and distance (in kms) and a legend/key showing specific age group population adjusted yearly (<1, <5, WCBA). | D4: 0.5 | E4: BHC, CHC, DH
A5: SQ 1.2 | B5: Proper filing system | C5: 1.2.1 In a filing cabinet/shelf/cupboard, in the designated service, and accessible by the officer on duty (except individual staff files) | D5: 0.5 | E5: BHC, CHC, DH
C6: 1.2.2 Minimum documents to be filled in the Administrative office (i) HMIS and (ii) clinic visit book | D6: 0.5 | E6: BHC, CHC, DH
C7: 1.2.3 (iii)Attendance sheet and (iv) monthly, quarterly and annual activity plans and (v) staff meeting notebook | D7: 0.5 | E7: BHC, CHC, DH
C8: 1.2.4 (vi) Financial file and (vii) community contribution register | D8: 0.5 | E8: BHC, CHC, DH
C9: 1.2.5 Minimum documents to be filled include CHS room: (ix) CHW supervision visit book; (x) clinic health committee meeting minutes | D9: 0.5 | E9: BHC, CHC, DH
A10: SQ 1.3 | B10: Staff duty roster | C10: The staff duty roster is regularly updated and prominently displayed to both staff and patients. The roster includes the schedule for the current month, the assigned duties of each staff member and the phone numbers of on-duty staff. | D10: 1 | E10: BHC, CHC, DH
A11: SQ 1.4 | B11: Technical meetings | C11: Technical Meetings (Management Committee Meetings & Clinical Staff Meetings) are scheduled on a monthly basis. QI committee meetings can alternate with clinical staff meetings; with 2 weeks between meetings. Minutes are taken during each meeting and include the date of the meeting, progress updates on the implementation of previous recommendations or actions, a list of new recommendations or decisions, and the chairman's signature. Records include three complete Clinical Staff Meetings and one quarterly Management Committee Meeting with detailed minutes. | D11: 4 | E11: BHC, CHC, DH
A12: SQ 1.5 | B12: Standard referral sheets | C12: At least 10 (empty) standard referral sheets are present during the evaluation | D12: 1 | E12: BHC, CHC, DH
A13: SQ 1.6 | B13: Availability of dedicated mobile phone for communication between health facility and general hospital | C13: A functional and charged mobile phone with a minimum call credit of AFS200. At minimum, the phone must store contact details of the Medical Director of the District Hospital, health facility staff, other Health Facility in-charges within the district, district health department, and the SP contact. | D13: 1 | E13: BHC, CHC, DH
A14: SQ 1.7 | B14: HMIS reports (sent to SP offices and MoPH) | C14: The transmission of HMIS reports occurs on a monthly basis, and a signed receipt of acknowledgement, both from the SP provincial offices and the MoPH is available. | D14: 1 | E14: BHC, CHC, DH
A15: SQ 1.8 | B15: HMIS reports (assessed concerning priority problems) | C15: Each quarter, four priority health problems are monitored and the data in the report has been updated until the month preceding the supervisor's visit. Additionally, the report includes a graphical representation of the health facility's quality score (presented in an "all or nothing" format). This score is derived from a monthly summary of the health problem classifications recorded in the General register at the end of each month. | D15: 1 | E15: BHC, CHC, DH
A16: SQ 1.9 | B16: Health Shura meetings | C16: Health Shura meetings are conducted on a monthly basis and meeting minutes are available. The monthly minutes include (i) the date of the meeting; (ii) a signed list of participants; (iii) follow-up of decisions taken during the previous meeting; (iv) a list of developed recommendations or decisions made; (v) signature of the chairman. | D16: 2 | E16: BHC, CHC, DH
A17: QQM Structural Quality - Domain 2: Hygiene
A18: SQ 2.1 | B18: Fence health facility available and well-maintained | C18: There is fencing or a wall (at least 1.5m in height) in good condition (no cracks) around the area of the health facility that can be closed at night (except riverine areas) | D18: 1 | E18: BHC, CHC, DH
A19: SQ 2.2 | B19: Garbage bin | C19: The courtyard has a garbage bin with a lid that is easily accessible to clients, and it is not full at the time of the evaluation. | D19: 1 | E19: BHC, CHC, DH
A20: SQ 2.3 | B20: Latrines/toilets | C20: 2.3.1 At least four water closet functional latrines/toilets (either the flushable squatting closet or the sitting closet) two for staff: Male and female, two for patients: Male and female. Toilets have a written and a pictorial sign. | D20: 1 | E20: BHC, CHC, DH
C21: 2.3.2 Floor without fissures | D21: 0.5 | E21: BHC, CHC, DH
C22: 2.3.3 Recently cleaned without visible fecal matter | D22: 0.5 | E22: BHC, CHC, DH
C23: 2.3.4 Door lockable from the inside, ceiling and super structure with roofing, without flies and no smell | D23: 0.5 | E23: BHC, CHC, DH
C24: 2.3.5 Hand hygiene/ sinks are located at the toilets AND running water is available (either sourced from a container or from piped water supply) AND soap or liquid soap, or detergent available at the sink. | D24: 0.5 | E24: BHC, CHC, DH
A25: SQ 2.4 | B25: Showers | C25: 2.4.1 At least two bathing facilities; one for men one for women (with floor without fissures, Door lockable from the inside, super structure with roofing) (in case of BHC one bathing facility (for women only); in case of CHC at least two; one for men and one for women) | D25: 1 | E25: BHC, CHC, DH
C26: 2.4.2 Bathing facility with running water, or container with at the least 20 L of water | D26: 0.5 | E26: BHC, CHC, DH
C27: 2.4.3 Evacuation of the waste water in a sanitation pit | D27: 0.5 | E27: BHC, CHC, DH
A28: SQ 2.5 | B28: Waste pit | C28: 2.5.1 Waste disposal pit minimum 4 meters deep, lined with clay, concrete or brick or plastic, it is fenced and has a bright flag | D28: 12 | E28: BHC, CHC, DH
C29: 2.5.2 The waste pit is a minimum of 15 meters from the health facility, minimum of 50 meters from a household, and 100 meters from a water source except in cases where the available surface area does not allow for these distances | E29: BHC, CHC, DH
C30: 2.5.3 Health Care Waste is not visible (covered by at the least 10 cm of soil or lime) | E30: BHC, CHC, DH
C31: 2.5.4 The health facility maintains a register indicating the date of the creation of the pit(s), and the location (s) | E31: BHC, CHC, DH
A32: SQ 2.6 | B32: Courtyard clean | D32: 1 | E32: BHC, CHC, DH
A33: SQ 2.7 | B33: Sterilization | C33: 2.7.1 Sterilizer functional (eg Autoclave) | D33: 3 | E33: BHC, CHC, DH
C34: 2.7.2 Sterilization protocol available and followed (medical personnel present can explain the protocol or demonstrate the process). When explaining the staff should at the least cover: (i) how items are arranged/packed; (ii) explain sterilization time for packed and unpacked items, and (iii) how to unload the items from the sterilizer | E34: BHC, CHC, DH
A35: SQ 2.8 | B35: Hygienic conditions assured during wound dressing and injections | C35: 2.8 1 Yellow and Red Bins for medical waste with lid and foot pedal, lined with bag and not full | D35: 2 | E35: BHC, CHC, DH
C36: 2.8.2 Security box for needles well positioned, and used (and not full) | E36: BHC, CHC, DH
C37: 2.8.3 Needle cutter available and used | E37: BHC, CHC, DH
C38: 2.8.4 Container/bowl with lid containing disinfectant used for putting used instruments | E38: BHC, CHC, DH
A39: SQ 2.9 | B39: Disposal of Health Care Waste | C39: Waste is segregated into three bin categories for proper disposal in accordance with national norms. None of the bins should be full or over-flowing. i) Non-contaminated waste, which includes general or municipal waste such as food items, carton boxes, wrappings, and garbage are placed in lined Black Bins equipped with lids and foot pedals and the waste bin is not full; and, ii) Contaminated health care waste, which includes infectious hazardous materials like used medical equipment, linens, gauze, syringes, catheter, iv cannula, gloves, serum bottles, and more are placed in cellophane-lined Yellow Bins with lids and foot pedals; and, iii) Organic health care waste including body parts, placenta, removed teeth, body fluids, suction machine secretions, expired blood, and other biohazardous materials are placed in cellophane-lined Red Bins with lids and foot pedals; and, iv) Availability of proper protective gear, including caps, masks, gumboots or enclosed shoes, plastic aprons, and thick plastic/rubber gloves. | D39: 6 | E39: BHC, CHC, DH
A40: SQ 2.1 | B40: COVID-19 prevention | C40: 2.10.1 i) Masks are available and used by staff ii) Alcohol handwashing solution is available for staff and patients in at the least (i) OPD and (ii) MCH section and (iii) EPI iii) COVID-19 prevention posters visible for patients in waiting room for OPD, and consultation room, and MCH section, and EPI section | D40: 3 | E40: BHC, CHC, DH
A41: QQM Structural Quality - Domain 3: OPD/ Curative consultations
A42: SQ 3.1 | B42: Good conditions in waiting area | C42: Separate waiting area for women and men, sufficient benches and or chairs protected against sun and rain and waiting area is not inside the consultation room. | D42: 1 | E42: BHC, CHC, DH
A43: SQ 3.2 | B43: Drugs which are available free of charge displayed to the public | C43: Up-to-date list of free-of-charge drugs and items easily visible and displayed in the waiting area of the consultation room. | D43: 1 | E43: BHC, CHC, DH
A44: SQ 3.3 | B44: Waiting card (or token) system with numbers | C44: Existence and use of waiting card (or token) system with numbers | D44: 1 | E44: BHC, CHC, DH
A45: SQ 3.4 | B45: Consultation room in good condition | C45: 3.4.1 - Walls with durable materials well painted, floor paved with cement without fissures, undamaged ceiling - Consultation room and waiting space separated assuring confidentiality - Windows with curtains - Functional door with functional lock - Running water (tap or water dispenser) with handwashing soap/liquid and clean towel available and used between patients | D45: 5 | E45: BHC, CHC, DH
